czech_simpleqa/__init__.py
czech_simpleqa/czech_simpleqa.csv.gz
czech_simpleqa/eval.py
czech_simpleqa/grading_template.py
czech_simpleqa-0.1.0.dist-info/METADATA
czech_simpleqa-0.1.0.dist-info/WHEEL
czech_simpleqa-0.1.0.dist-info/licenses/LICENSE
czech_simpleqa-0.1.0.dist-info/RECORD
