Metadata-Version: 2.4
Name: czech-simpleqa
Version: 0.1.0
Summary: How Well Can Language Models Answer Questions in Czech?
Author-email: Jan Cervenka <jan.cervenka@yahoo.com>
License-File: LICENSE
Requires-Python: >=3.12
Requires-Dist: anthropic>=0.42.0
Requires-Dist: instructor>=1.7.2
Requires-Dist: openai>=1.59.4
Requires-Dist: pandas>=2.2.3
Requires-Dist: pydantic>=2.10.4
Requires-Dist: tqdm>=4.67.1
